moldcast/__about__.py
moldcast/__init__.py
moldcast/__main__.py
moldcast/cli.py
moldcast-0.1.0.dist-info/METADATA
moldcast-0.1.0.dist-info/WHEEL
moldcast-0.1.0.dist-info/entry_points.txt
moldcast-0.1.0.dist-info/top_level.txt
moldcast-0.1.0.dist-info/zip-safe
moldcast-0.1.0.dist-info/RECORD
